{
  "name": "Lovlyboy-X1 Bot",
  "description": "A powerful multi-feature WhatsApp bot.",
  "repository": "https://github.com/Samin123123/Lovlyboy-x1",
  "keywords": ["whatsapp", "bot", "lovlyboy-x1", "md"],
  "env": {
    "BOT_NAME": {
      "description": "Your bot name",
      "value": "lovlyboy-x1"
    },
    "OWNER_NAME": {
      "description": "Your name",
      "value": "Samin"
    },
    "OWNER_NUMBER": {
      "description": "Your WhatsApp number",
      "value": "919242172553"
    },
    "SESSION_ID": {
      "description": "Scan QR to get session or use pre-generated ID",
      "value": ""
    },
    "DATABASE_URL": {
      "description": "MongoDB/SQL database connection string",
      "value": ""
    }
  }
}
